odoo/addons/web_listview_range_select/README.rst
odoo/addons/web_listview_range_select/__init__.py
odoo/addons/web_listview_range_select/__manifest__.py
odoo/addons/web_listview_range_select/i18n/es.po
odoo/addons/web_listview_range_select/i18n/hr.po
odoo/addons/web_listview_range_select/i18n/web_listview_range_select.pot
odoo/addons/web_listview_range_select/i18n/zh_CN.po
odoo/addons/web_listview_range_select/readme/CONTRIBUTORS.rst
odoo/addons/web_listview_range_select/readme/DESCRIPTION.rst
odoo/addons/web_listview_range_select/readme/ROADMAP.rst
odoo/addons/web_listview_range_select/readme/USAGE.rst
odoo/addons/web_listview_range_select/static/description/icon.png
odoo/addons/web_listview_range_select/static/description/index.html
odoo/addons/web_listview_range_select/static/src/js/web_listview_range_select.js
odoo/addons/web_listview_range_select/templates/assets.xml
odoo13_addon_web_listview_range_select-13.0.1.0.1.dev4.dist-info/METADATA
odoo13_addon_web_listview_range_select-13.0.1.0.1.dev4.dist-info/WHEEL
odoo13_addon_web_listview_range_select-13.0.1.0.1.dev4.dist-info/top_level.txt
odoo13_addon_web_listview_range_select-13.0.1.0.1.dev4.dist-info/RECORD
